ocular/__init__.py
ocular/exceptions.py
ocular/processor.py
ocular/constants/__init__.py
ocular/constants/container_statuses.py
ocular/constants/event_types.py
ocular/constants/pod_conditions.py
ocular/constants/pod_lifecycle.py
ocular/constants/pod_statuses.py
ocular-0.1.7.dist-info/LICENSE
ocular-0.1.7.dist-info/METADATA
ocular-0.1.7.dist-info/WHEEL
ocular-0.1.7.dist-info/top_level.txt
ocular-0.1.7.dist-info/RECORD
