Metadata-Version: 2.1
Name: ocular
Version: 0.1.7
Summary: A tool for observing Kubernetes pods' statuses in real time.
Home-page: https://github.com/polyaxon/ocular
Author: Mourad Mourafiq
Author-email: mourad@polyaxon.com
Maintainer: Mourad Mourafiq
Maintainer-email: mourad@polyaxon.com
License: MIT
Keywords: polyaxon,aws,azure,google cloud storage,k8s,kubernetes,docker
Platform: any
Classifier: Programming Language :: Python
Classifier: Operating System :: OS Independent
Classifier: Intended Audience :: Developers
Classifier: Intended Audience :: Science/Research
Classifier: Topic :: Scientific/Engineering :: Artificial Intelligence
Requires-Dist: hestia (>=0.3.1)
Requires-Dist: kubernetes (>=10.0.1)
Requires-Dist: six (>=1.12.0)
